cryptostore/__init__.py
cryptostore/collector.py
cryptostore/config.py
cryptostore/cryptostore.py
cryptostore/engines.py
cryptostore/exceptions.py
cryptostore/log.py
cryptostore/spawn.py
cryptostore/util.py
cryptostore/aggregator/__init__.py
cryptostore/aggregator/aggregator.py
cryptostore/aggregator/cache.py
cryptostore/aggregator/kafka.py
cryptostore/aggregator/redis.py
cryptostore/aggregator/util.py
cryptostore/bin/__init__.py
cryptostore/bin/cryptostore.py
cryptostore/data/__init__.py
cryptostore/data/arctic.py
cryptostore/data/elastic.py
cryptostore/data/gc.py
cryptostore/data/gd.py
cryptostore/data/influx.py
cryptostore/data/parquet.py
cryptostore/data/s3.py
cryptostore/data/storage.py
cryptostore/data/store.py
cryptostore/plugin/__init__.py
cryptostore/plugin/backfill.py
cryptostore/plugin/controller.py
cryptostore/plugin/plugin.py
cryptostore-0.4.0.dist-info/LICENSE
cryptostore-0.4.0.dist-info/METADATA
cryptostore-0.4.0.dist-info/WHEEL
cryptostore-0.4.0.dist-info/entry_points.txt
cryptostore-0.4.0.dist-info/top_level.txt
cryptostore-0.4.0.dist-info/RECORD
